mpl_pe_fancy_bar/__init__.py
mpl_pe_fancy_bar/_version.py
mpl_pe_fancy_bar/bar_with_icon.py
mpl_pe_fancy_bar/fancy_bar.py
mpl_pe_fancy_bar/paths_stretcher.py
mpl_pe_fancy_bar/tests/__init__.py
mpl_pe_fancy_bar/tests/test_example.py
mpl_pe_fancy_bar-0.1.0.dist-info/LICENSE
mpl_pe_fancy_bar-0.1.0.dist-info/METADATA
mpl_pe_fancy_bar-0.1.0.dist-info/WHEEL
mpl_pe_fancy_bar-0.1.0.dist-info/top_level.txt
mpl_pe_fancy_bar-0.1.0.dist-info/RECORD
